MANIFEST.in
README.md
requirements.txt
service.encode.txt
setup.py
co6co/__init__.py
co6co/demo.test.py
co6co/setupUtils.py
co6co.egg-info/PKG-INFO
co6co.egg-info/SOURCES.txt
co6co.egg-info/dependency_links.txt
co6co.egg-info/top_level.txt
co6co.egg-info/zip-safe
co6co/data/__init__.py
co6co/data/excell.py
co6co/database/__init__.py
co6co/database/sqlite.py
co6co/enums/__init__.py
co6co/storage/Dict.py
co6co/storage/__init__.py
co6co/task/__init__.py
co6co/task/pools.py
co6co/task/thread.py
co6co/task/utils.py
co6co/utils/File.py
co6co/utils/__init__.py
co6co/utils/gps.py
co6co/utils/hash.py
co6co/utils/http.py
co6co/utils/json_util.py
co6co/utils/log.py
co6co/utils/modules.py
co6co/utils/network.py
co6co/utils/singleton.py
co6co/utils/source.py
co6co/utils/tool_util.py
co6co/utils/win.py